MANIFEST.in
README.rst
buildout.cfg
setup.cfg
setup.py
docs/CHANGES.rst
docs/CONTRIBUTORS.rst
docs/LICENSE.txt
src/bobtemplates/__init__.py
src/bobtemplates.jpcw.egg-info/PKG-INFO
src/bobtemplates.jpcw.egg-info/SOURCES.txt
src/bobtemplates.jpcw.egg-info/dependency_links.txt
src/bobtemplates.jpcw.egg-info/entry_points.txt
src/bobtemplates.jpcw.egg-info/namespace_packages.txt
src/bobtemplates.jpcw.egg-info/not-zip-safe
src/bobtemplates.jpcw.egg-info/requires.txt
src/bobtemplates.jpcw.egg-info/top_level.txt
src/bobtemplates/jpcw/__init__.py
src/bobtemplates/jpcw/hooks.py
src/bobtemplates/jpcw/basic_namespace/.mrbob.ini
src/bobtemplates/jpcw/basic_namespace/MANIFEST.in
src/bobtemplates/jpcw/basic_namespace/README.rst.bob
src/bobtemplates/jpcw/basic_namespace/setup.cfg
src/bobtemplates/jpcw/basic_namespace/setup.py.bob
src/bobtemplates/jpcw/basic_namespace/docs/CHANGES.rst.bob
src/bobtemplates/jpcw/basic_namespace/docs/CONTRIBUTORS.rst.bob
src/bobtemplates/jpcw/basic_namespace/docs/LICENSE.GPL
src/bobtemplates/jpcw/basic_namespace/docs/LICENSE.txt.bob
src/bobtemplates/jpcw/basic_namespace/src/+pkg_ns+/__init__.py
src/bobtemplates/jpcw/basic_namespace/src/+pkg_ns+/+pkg_project+/__init__.py.bob
src/bobtemplates/jpcw/tests/__init__.py
src/bobtemplates/jpcw/tests/test_hooks.py