Metadata-Version: 1.1
Name: bobtemplates.jpcw
Version: 0.2
Summary: bobtemplates basic_namespace
Home-page: https://github.com/jpcw/bobtemplates.jpcw
Author: Jean-Philippe Camguilhem
Author-email: jp.camguilhem@gmail.com
License: BSD
Keywords: bobtemplates
Platform: any
Classifier: Programming Language :: Python
Classifier: Programming Language :: Python :: Implementation :: CPython
Classifier: Programming Language :: Python :: Implementation :: PyPy
Classifier: Programming Language :: Python :: 2.6
Classifier: Programming Language :: Python :: 2.7
Classifier: Programming Language :: Python :: 3
Classifier: Programming Language :: Python :: 3.2
Classifier: Programming Language :: Python :: 3.3
Classifier: Programming Language :: Python :: 3.4
Classifier: License :: OSI Approved :: BSD License
